plapi/__init__.py
plapi/hello_world.py
plapi_example_api-0.0.5.dist-info/LICENSE
plapi_example_api-0.0.5.dist-info/METADATA
plapi_example_api-0.0.5.dist-info/WHEEL
plapi_example_api-0.0.5.dist-info/top_level.txt
plapi_example_api-0.0.5.dist-info/RECORD
